<?xml version="1.0"?>
<!DOCTYPE hibernate-mapping PUBLIC "-//Hibernate/Hibernate Mapping DTD 3.0//EN"
"http://hibernate.sourceforge.net/hibernate-mapping-3.0.dtd">
<!-- Generated Nov 20, 2018 11:32:29 AM by Hibernate Tools 3.5.0.Final -->
<hibernate-mapping>
    <class name="com.miBudget.entities.UserAccountObject" table="user_accounts">
        <id name="id" type="int">
            <column name="id" />
            <generator class="assigned" />
        </id>
        <property name="userId" type="int">
            <column name="user_id" />
        </property>
        <property name="accountId" type="java.lang.String">
            <column name="account_id" />
        </property>
        <property name="availableBalance" type="double">
            <column name="available_balance" />
        </property>
        <property name="currencyCode" type="java.lang.String">
            <column name="currency_code" />
        </property>
        <property name="currentBalance" type="double">
            <column name="current_balance" />
        </property>
        <property name="limit" type="double" access="field">
            <column name="_limit" />
        </property>
        <property name="item__id" type="int">
            <column name="item__id" />
        </property>
        <property name="mask" type="java.lang.String">
            <column name="mask" />
        </property>
        <property name="accountName" type="java.lang.String">
            <column name="account_name" />
        </property>
        <property name="officialName" type="java.lang.String">
            <column name="official_name" />
        </property>
        <property name="type" type="java.lang.String">
            <column name="_type" />
        </property>
        <property name="subType" type="java.lang.String">
            <column name="subtype" />
        </property>
    </class>
</hibernate-mapping>
